<?xml version='1.0' encoding='UTF-8'?>
<ns0:alto xmlns:ns0="http://www.loc.gov/standards/alto/ns-v4#" xmlns:xsi="http://www.w3.org/2001/XMLSchema-instance" xsi:schemaLocation="http://www.loc.gov/standards/alto/ns-v4# http://www.loc.gov/standards/alto/v4/alto-4-2.xsd">
  <ns0:Description>
    <ns0:MeasurementUnit>pixel</ns0:MeasurementUnit>
    <ns0:sourceImageInformation>
      <ns0:fileName>image_002.jpg</ns0:fileName>
    </ns0:sourceImageInformation>
  </ns0:Description>
  <ns0:Tags>
    <ns0:OtherTag ID="BT100" LABEL="header" DESCRIPTION="block type header" /><ns0:OtherTag ID="BT101" LABEL="Pricing" DESCRIPTION="block type Pricing" /><ns0:OtherTag ID="BT102" LABEL="Metadata" DESCRIPTION="block type Metadata" /><ns0:OtherTag ID="BT103" LABEL="Date(s)" DESCRIPTION="block type Date(s)" /><ns0:OtherTag ID="BT104" LABEL="Column" DESCRIPTION="block type Column" /><ns0:OtherTag ID="BT105" LABEL="footer" DESCRIPTION="block type footer" /><ns0:OtherTag ID="BT106" LABEL="Motto" DESCRIPTION="block type Motto" />
  </ns0:Tags>
  <ns0:Layout>
    <ns0:Page WIDTH="1400" HEIGHT="1982" PHYSICAL_IMG_NR="1" ID="eSc_dummypage_">
      <ns0:PrintSpace HPOS="0" VPOS="0" WIDTH="1400" HEIGHT="1982">
        <ns0:TextBlock HPOS="251" VPOS="220" WIDTH="541" HEIGHT="1617" ID="tr_1701875458" TAGREFS="BT104">
          <ns0:Shape><ns0:Polygon POINTS="251 220 742 220 792 1816 298 1837" /></ns0:Shape>
        </ns0:TextBlock>
        <ns0:TextBlock HPOS="760" VPOS="207" WIDTH="555" HEIGHT="1596" ID="tr_1701875459" TAGREFS="BT104">
          <ns0:Shape><ns0:Polygon POINTS="760 214 1278 207 1315 1776 798 1803" /></ns0:Shape>
        </ns0:TextBlock>
        <ns0:TextBlock HPOS="346" VPOS="130" WIDTH="818" HEIGHT="79" ID="tr_1702555733" TAGREFS="BT100">
          <ns0:Shape><ns0:Polygon POINTS="346 144 1164 130 1164 187 346 209" /></ns0:Shape>
        </ns0:TextBlock>
      </ns0:PrintSpace>
    </ns0:Page>
  </ns0:Layout>
</ns0:alto>